subdivide/__init__.py
subdivide/cut.py
subdivide/strategies.py
subdivide/util.py
subdivide-1.0.2.dist-info/METADATA
subdivide-1.0.2.dist-info/WHEEL
subdivide-1.0.2.dist-info/top_level.txt
subdivide-1.0.2.dist-info/RECORD
