Metadata-Version: 2.1
Name: subdivide
Version: 1.0.2
Summary: Subdivides lines by several methods.
Home-page: https://github.com/davenquinn/subdivide
Author: Daven Quinn
Author-email: code@davenquinn.com
Maintainer: Daven Quinn
Maintainer-email: code@davenquinn.com
License: MIT
Platform: UNKNOWN
Classifier: Intended Audience :: Science/Research
Classifier: Operating System :: OS Independent
Classifier: Programming Language :: Python
Classifier: Topic :: Scientific/Engineering :: GIS
Requires-Dist: numpy
Requires-Dist: shapely
